<?xml version="1.0" encoding="UTF-8"?>

<metric-definition xmlns:xsi="http://www.w3.org/2001/XMLSchema-instance"
    xmlns="http://www.optimyth.com/schema/definitions/metric" 
    version="1.1">

  <metric id="OPT.sqlCalls" unit="" aggregation="sum" aggregationScope="program">

    <!-- Criteria values: better is, scopes, language parsers, etc. -->
    <criteria-values>
      <criterium-value ref="OPT.CRITERIUM_VALUE.METRIC_TYPE.SIZE" />
      <criterium-value ref="OPT.CRITERIUM_VALUE.METRIC_HIERARCHY.SIZE.DATABASE" />
      <criterium-value ref="OPT.CRITERIUM_VALUE.BETTER_IS.NA" />
      <criterium-value ref="OPT.CRITERIUM_VALUE.SCOPE.SYSTEM" />
      <criterium-value ref="OPT.CRITERIUM_VALUE.SCOPE.PROGRAM" />
      <criterium-value ref="OPT.CRITERIUM_VALUE.LANGUAGE_PARSER.PLSQL" />
      <criterium-value ref="OPT.CRITERIUM_VALUE.LANGUAGE_PARSER.SQL" />
      <criterium-value ref="OPT.CRITERIUM_VALUE.LANGUAGE_PARSER.TRANSACTSQL" />
    </criteria-values>

    <!-- Valid range -->
    <range>
      <minimum value="0" included="true" />
      <maximum value="+inf" included="false" />
    </range>

    <!-- Metric thresholds (up to three) -->
    <thresholds />

    <!-- Metric parameters (applies to implementations that reference them) -->
    <parameters />

    <!-- Metric implementations for each language parser -->
    <implementations>

      <language-parser ref="OPT.CRITERIUM_VALUE.LANGUAGE_PARSER.PLSQL">
        <internal-name id="OPT.PLSQL.SIZE.STATEMENTS" />
        <java-class>com.als.plsql.metrics.StatementsCountPlsqlMetricRule</java-class>
        <java-version>1.5</java-version>
        <parameters />
      </language-parser>

      <language-parser ref="OPT.CRITERIUM_VALUE.LANGUAGE_PARSER.SQL">
        <internal-name id="OPT.SQL.SIZE.STATEMENTS" />
        <java-class>com.optimyth.sql.metrics.AstSqlSizeRule</java-class>
        <java-version>1.5</java-version>
        <parameters />
      </language-parser>

      <language-parser ref="OPT.CRITERIUM_VALUE.LANGUAGE_PARSER.TRANSACTSQL">
        <internal-name id="OPT.TRANSACTSQL.SIZE.STATEMETS" />
        <java-class>com.optimyth.qaking.tsql.metrics.StatementsCountMetricRule</java-class>
        <java-version>1.5</java-version>
        <parameters />
      </language-parser>

      
      <reference><![CDATA[Optimyth (http://www.optimyth.com)]]></reference>

    </implementations>

    <!-- Code examples for each language parser -->
    <code-examples>
    <language-parser ref="OPT.CRITERIUM_VALUE.LANGUAGE_PARSER.PLSQL">
        <code-example name="metricCodeExamplePlsql" result-value="1">
<![CDATA[
SET ECHO OFF
SET HEAD OFF
SET PAGESIZE 0
SET LINESIZE 375
SET FEEDBACK OFF
SET COLSEP '|'

SPOOL &1/&5\_01a_sel_alarma.rpt

 var fecha_corte_alarma VARCHAR2(20);

 exec :fecha_corte_alarma := to_date('01/01/'||to_char(&2 - &6)   --SQL CALL 1
 , 'dd/mm/yyyy');

SPOOL OFF
SET HEAD ON
SET FEEDBACK ON
SET ECHO ON
DISCONNECT;
EXIT;
]]>
        </code-example>
      </language-parser>
    <language-parser ref="OPT.CRITERIUM_VALUE.LANGUAGE_PARSER.SQL">
        <code-example name="metricCodeExampleSql" result-value="1">
<![CDATA[
SET @sqlCommand = 'SELECT ' + @columnList + ' FROM customers WHERE City = ' + @city
EXEC (@sqlCommand)           --SQL CALL 1
]]>
        </code-example>
      </language-parser>
    <language-parser ref="OPT.CRITERIUM_VALUE.LANGUAGE_PARSER.TRANSACTSQL">
        <code-example name="metricCodeExampleTransactsql" result-value="1">
<![CDATA[
USE master; 
EXEC ('USE AdventureWorks2012; SELECT BusinessEntityID, JobTitle FROM HumanResources.Employee;');  --SQL CALL 1
]]>
        </code-example>
      </language-parser>
    </code-examples>

    <!-- Internationalizations for each human language -->
    <i18ns>
    <i18n ref="OPT.LANGUAGE.SPANISH">

      <name><![CDATA[Llamadas SQL]]></name>
      
      <description>
<![CDATA[
Número de operaciones SQL (statements), utilizando análisis estático.
]]></description>

      <implementation-descriptions>

        <implementation-description ref="OPT.CRITERIUM_VALUE.LANGUAGE_PARSER.PLSQL">
<![CDATA[
Cuenta el número de insert, delete, update, schemaOperations (create+alter+drop), sqlCalls (exec+ execute immediate) y select (en este último, no se cuentan las select anidadas, ni declaradas dentro de vistas, pero si las declaradas en cursores).
]]>
        </implementation-description>

        <implementation-description ref="OPT.CRITERIUM_VALUE.LANGUAGE_PARSER.SQL">
<![CDATA[
Cuenta el número de insert, delete, update, schemaOperations (create+alter+drop), sqlCalls (exec+ execute immediate) y select (en este último, no se cuentan las select anidadas, ni declaradas dentro de vistas, pero si las declaradas en cursores).
]]>
        </implementation-description>

        <implementation-description ref="OPT.CRITERIUM_VALUE.LANGUAGE_PARSER.TRANSACTSQL">
<![CDATA[
Cuenta el número de insert, delete, update, schemaOperations (create+alter+drop), sqlCalls (execute) y select (en este último, no se cuentan las select anidadas, ni declaradas dentro de vistas, pero si las declaradas en cursores).
]]>
        </implementation-description>

      </implementation-descriptions>

      <parameters />

    </i18n>

    <i18n ref="OPT.LANGUAGE.ENGLISH">

      <name><![CDATA[SQL calls]]></name>
      
      <description>
<![CDATA[
SQL operations (statements) counts, using static analysis.
]]>
      </description>

      <implementation-descriptions>

        <implementation-description ref="OPT.CRITERIUM_VALUE.LANGUAGE_PARSER.PLSQL">
<![CDATA[
Counts the number of insert, delete, update, schemaOperations (create+alter+drop), sqlCalls (exec+execute immediate) and select (in the latter, do not count the nested selects, or those declared within a view, but selects declared in cursors will be taken into account).
]]>
        </implementation-description>

        <implementation-description ref="OPT.CRITERIUM_VALUE.LANGUAGE_PARSER.SQL">
<![CDATA[
Counts the number of insert, delete, update, schemaOperations (create+alter+drop), sqlCalls (exec+execute immediate) and select (in the latter, do not count the nested selects, or those declared within a view, but selects declared in cursors will be taken into account).
]]>
        </implementation-description>

        <implementation-description ref="OPT.CRITERIUM_VALUE.LANGUAGE_PARSER.TRANSACTSQL">
<![CDATA[
Counts the number of insert, delete, update, schemaOperations (create+alter+drop), sqlCalls (execute) and select (in the latter, do not count the nested selects, or those declared within a view, but selects declared in cursors will be taken into account).
]]>
        </implementation-description>

      </implementation-descriptions>

      <parameters />

    </i18n>
    </i18ns>
  </metric>
</metric-definition>
